serenity_types/__init__.py
serenity_types/catalog/model.py
serenity_types/marketdata/__init__.py
serenity_types/marketdata/marks.py
serenity_types/platform/__init__.py
serenity_types/platform/core.py
serenity_types/portfolio/__init__.py
serenity_types/portfolio/core.py
serenity_types/pricing/__init__.py
serenity_types/pricing/core.py
serenity_types/pricing/derivatives/__init__.py
serenity_types/pricing/derivatives/options/__init__.py
serenity_types/pricing/derivatives/options/valuation.py
serenity_types/pricing/derivatives/options/volsurface.py
serenity_types/pricing/derivatives/rates/__init__.py
serenity_types/pricing/derivatives/rates/yield_curve.py
serenity_types/refdata/__init__.py
serenity_types/refdata/asset.py
serenity_types/refdata/currency.py
serenity_types/refdata/derivatives.py
serenity_types/refdata/exposure.py
serenity_types/refdata/futures.py
serenity_types/refdata/index.py
serenity_types/refdata/legacy.py
serenity_types/refdata/network.py
serenity_types/refdata/options.py
serenity_types/refdata/organization.py
serenity_types/refdata/sector.py
serenity_types/refdata/symbology.py
serenity_types/refdata/token.py
serenity_types/risk/__init__.py
serenity_types/risk/factor.py
serenity_types/risk/scenarios.py
serenity_types/risk/var.py
serenity_types/utils/__init__.py
serenity_types/utils/common.py
serenity_types/utils/serialization.py
serenity_types/valuation/__init__.py
serenity_types/valuation/core.py
serenity.types.python-0.0.30.dist-info/LICENSE
serenity.types.python-0.0.30.dist-info/WHEEL
serenity.types.python-0.0.30.dist-info/METADATA
serenity.types.python-0.0.30.dist-info/RECORD
